pyoteapp/PYOTE.bat
pyoteapp/SER.py
pyoteapp/__init__.py
pyoteapp/autocorrtools.py
pyoteapp/blockIntegrateUtils.py
pyoteapp/checkForNewerVersion.py
pyoteapp/csvreader.py
pyoteapp/diffraction-table.p
pyoteapp/errorBarUtils.py
pyoteapp/example-penumbral.csv
pyoteapp/exponentialEdgeUtilities.py
pyoteapp/false_positive.py
pyoteapp/fixedPrecision.py
pyoteapp/genDiffraction.py
pyoteapp/gui.py
pyoteapp/helpDialog.py
pyoteapp/iterative_logl_functions.py
pyoteapp/likelihood_calculations.py
pyoteapp/model-help.pdf
pyoteapp/noiseUtils.py
pyoteapp/pyote-info.pdf
pyoteapp/pyote.py
pyoteapp/pyote_modelling_utility_functions.py
pyoteapp/run-pyote-mac.bat
pyoteapp/showVideoFrames.py
pyoteapp/solverUtils.py
pyoteapp/subframe_timing_utilities.py
pyoteapp/timestampDialog.py
pyoteapp/timestampUtils.py
pyoteapp/version.py
pyoteapp/model-examples/LCP_dod-example.p
pyoteapp/model-examples/diffraction_miss_shotnoise_1.0_readnoise_20.0.csv
pyoteapp/model-examples/diffraction_with_central_spot_shotnoise_1.0_readnoise_20.0.csv
pyoteapp/model-examples/disk_on_disk_annular_shotnoise_1.0_readnoise_20.0.csv
pyoteapp/model-examples/disk_on_disk_annular_shotnoise_1.0_readnoise_20.0.pyote_log.txt
pyoteapp/model-examples/edge_on_disk_miss_shotnoise_0.0_readnoise_10.0.csv
pyoteapp/model-examples/edge_on_disk_standard_penumbral_D55_R35_shotnoise_2.0_readnoise_20.0.csv
pyoteapp/model-examples/fit_metrics.txt
pyoteapp/model-examples/high-rho-diffraction_shotnoise_2.0_readnoise_20.0.csv
pyote-5.7.11.dist-info/LICENSE
pyote-5.7.11.dist-info/METADATA
pyote-5.7.11.dist-info/WHEEL
pyote-5.7.11.dist-info/top_level.txt
pyote-5.7.11.dist-info/RECORD
