Metadata-Version: 2.2
Name: pyote
Version: 5.7.11
Summary: pyote is a simplified subset of R-OTE
Home-page: https://github.com/bob-anderson-ok/py-ote
Author: Bob Anderson
Author-email: bob.anderson.ok@gmail.com
Maintainer: Bob Anderson
Maintainer-email: bob.anderson.ok@gmail.com
License: License :: OSI Approved :: MIT License
Keywords: desktop app,asteroid occultation timing extraction
Classifier: Development Status :: 5 - Production/Stable
Classifier: Intended Audience :: Science/Research
Classifier: Natural Language :: English
Classifier: License :: OSI Approved :: MIT License
Classifier: Operating System :: MacOS :: MacOS X
Classifier: Operating System :: Microsoft :: Windows
Classifier: Programming Language :: Python :: 3.7
Classifier: Programming Language :: Python :: Implementation :: CPython
Classifier: Topic :: Scientific/Engineering
License-File: LICENSE
Requires-Dist: pyqtgraph==0.12.4
Requires-Dist: opencv-python
Requires-Dist: astroquery
Requires-Dist: resource
Requires-Dist: scikit-image>=0.15.0
Requires-Dist: wheel
Requires-Dist: requests
Requires-Dist: pyephem
Requires-Dist: PyQt5
Requires-Dist: pandas
Requires-Dist: winshell; platform_system == "Windows"
Requires-Dist: pypiwin32; platform_system == "Windows"
Requires-Dist: matplotlib
Requires-Dist: numpy<=1.22
Requires-Dist: astropy
Requires-Dist: scikit-image
Requires-Dist: scipy
Requires-Dist: numba>=0.41.0
Requires-Dist: Adv2>=1.2.0
Requires-Dist: PyQt5
Requires-Dist: openpyxl
Requires-Dist: xlrd
Requires-Dist: xlsxwriter
Dynamic: author
Dynamic: author-email
Dynamic: classifier
Dynamic: description
Dynamic: home-page
Dynamic: keywords
Dynamic: license
Dynamic: maintainer
Dynamic: maintainer-email
Dynamic: requires-dist
Dynamic: summary
